{
    "Name": "Super Mushroom",
    "Product": "Super Mushroom",
    "SeedName": "Super Mushroom Seeds",
    "SeedDescription": "Grown only in summer, these mushrooms provide useful buffs year-round. Takes 7 days to mature and produces more every 3 days.",
    "Type": "Cooking",
    "Seasons": ["summer"],
    "Phases": [ 1, 1,1,1,1,1,1],
    "RegrowthPhase": 3,
    "HarvestWithScythe": false,
    "TrellisCrop": true,
    "Colors": null,
    "Bonus": {
        "MinimumPerHarvest": 2,
        "MaximumPerHarvest": 5,
        "MaxIncreasePerFarmLevel": 5,
        "ExtraChance": 0.4,
    },
    "SeedPurchasePrice": 550,
}
